{
	"configurations" : 
	[
		{
			"directories" : 
			[
				{
					"build" : ".",
					"jsonFile" : "directory-.-Debug-d0094a50bb2071803777.json",
					"minimumCMakeVersion" : 
					{
						"string" : "3.30"
					},
					"projectIndex" : 0,
					"source" : ".",
					"targetIndexes" : 
					[
						0
					]
				}
			],
			"name" : "Debug",
			"projects" : 
			[
				{
					"directoryIndexes" : 
					[
						0
					],
					"name" : "NetworkStorage",
					"targetIndexes" : 
					[
						0
					]
				}
			],
			"targets" : 
			[
				{
					"directoryIndex" : 0,
					"id" : "NetworkStorage::@6890427a1f51a3e7e1df",
					"jsonFile" : "target-NetworkStorage-Debug-56567ad3af6f0072a306.json",
					"name" : "NetworkStorage",
					"projectIndex" : 0
				}
			]
		}
	],
	"kind" : "codemodel",
	"paths" : 
	{
		"build" : "C:/Users/USER/Desktop/c/Network_Storage/cmake-build-debug",
		"source" : "C:/Users/USER/Desktop/c/Network_Storage"
	},
	"version" : 
	{
		"major" : 2,
		"minor" : 7
	}
}
